typedi/__init__.py
typedi/container.py
typedi/object_proxy.py
typedi/py.typed
typedi/resolution.py
typedi/typing_utils.py
typedi-0.6.0.dist-info/LICENCE
typedi-0.6.0.dist-info/METADATA
typedi-0.6.0.dist-info/WHEEL
typedi-0.6.0.dist-info/top_level.txt
typedi-0.6.0.dist-info/RECORD
