Metadata-Version: 2.1
Name: typedi
Version: 0.6.0
Summary: Simple yet powerful typed dependency injection container
Home-page: https://github.com/bshishov/typedi
Author: Boris Shishov
Author-email: borisshishov@gmail.com
License: MIT
Platform: any
Classifier: Development Status :: 4 - Beta
Classifier: License :: OSI Approved :: MIT License
Classifier: Intended Audience :: Developers
Classifier: Programming Language :: Python :: 3
Classifier: Programming Language :: Python :: 3.7
Classifier: Programming Language :: Python :: 3.8
Classifier: Programming Language :: Python :: 3.9
Classifier: Programming Language :: Python :: 3.10
Classifier: Operating System :: OS Independent
Classifier: Topic :: Software Development :: Libraries
Requires-Python: >=3.7
Provides-Extra: test
Requires-Dist: pytest (==7.1.2) ; extra == 'test'
Requires-Dist: coverage (==6.3.2) ; extra == 'test'
